bpy_widget/__init__.py
bpy_widget/py.typed
bpy_widget/widget.py
bpy_widget/core/__init__.py
bpy_widget/core/camera.py
bpy_widget/core/compositor_manager.py
bpy_widget/core/curve_utils.py
bpy_widget/core/data_import.py
bpy_widget/core/data_readers.py
bpy_widget/core/extension_manager.py
bpy_widget/core/geometry.py
bpy_widget/core/io_handlers.py
bpy_widget/core/lighting.py
bpy_widget/core/materials.py
bpy_widget/core/nodes.py
bpy_widget/core/point_cloud.py
bpy_widget/core/post_processing.py
bpy_widget/core/rendering.py
bpy_widget/core/scene.py
bpy_widget/core/setup_datafiles.py
bpy_widget/core/temp_files.py
bpy_widget/static/widget.css
bpy_widget/static/widget.js
bpy_widget-0.1.2.dist-info/METADATA
bpy_widget-0.1.2.dist-info/WHEEL
bpy_widget-0.1.2.dist-info/licenses/LICENSE
bpy_widget-0.1.2.dist-info/RECORD
