Metadata-Version: 2.4
Name: bpy-widget
Version: 0.1.2
Summary: Interactive Blender 3D viewport widget for notebooks with real-time Eevee Next rendering.
Project-URL: Homepage, https://github.com/bjoernbethge/bpy-widget
Project-URL: Repository, https://github.com/bjoernbethge/bpy-widget
Project-URL: Issues, https://github.com/bjoernbethge/bpy-widget/issues
Author-email: Björn Bethge <bjoern.bethge@gmail.com>
License: MIT
License-File: LICENSE
Keywords: 3d,blender,cycles,eevee,jupyter,marimo,notebook,rendering,visualization,widget
Classifier: Development Status :: 3 - Alpha
Classifier: Framework :: Jupyter
Classifier: Intended Audience :: Developers
Classifier: Intended Audience :: Science/Research
Classifier: License :: OSI Approved :: MIT License
Classifier: Programming Language :: Python :: 3
Classifier: Programming Language :: Python :: 3.11
Classifier: Topic :: Multimedia :: Graphics :: 3D Modeling
Classifier: Topic :: Scientific/Engineering :: Visualization
Requires-Python: >=3.11
Requires-Dist: anywidget>=0.9.18
Requires-Dist: bpy==4.5.4
Requires-Dist: httpx>=0.24.0
Requires-Dist: loguru>=0.7.3
Requires-Dist: numpy>=1.26.0
Requires-Dist: polars>=1.19.0
Requires-Dist: traitlets>=5.14.3
